v_program6/__init__.py
v_program6/__main__.py
ml_prm-0.1.dist-info/METADATA
ml_prm-0.1.dist-info/WHEEL
ml_prm-0.1.dist-info/entry_points.txt
ml_prm-0.1.dist-info/top_level.txt
ml_prm-0.1.dist-info/RECORD
