Metadata-Version: 2.1
Name: ml_prm
Version: 0.1
Summary: A Python package for machine learning projects including model training and evaluation.
Author: Arasu
Author-email: arasu6262@gmail.com
Classifier: Development Status :: 3 - Alpha
Classifier: Intended Audience :: Developers
Classifier: License :: OSI Approved :: MIT License
Classifier: Programming Language :: Python :: 3
Classifier: Programming Language :: Python :: 3.6
Classifier: Programming Language :: Python :: 3.7
Classifier: Programming Language :: Python :: 3.8
Classifier: Programming Language :: Python :: 3.9
Classifier: Programming Language :: Python :: 3.10
Classifier: Programming Language :: Python :: 3.11
Classifier: Operating System :: OS Independent
Requires-Python: >=3.6
Requires-Dist: scikit-learn>=0.24
Requires-Dist: numpy>=1.21
Requires-Dist: scipy>=1.7
Provides-Extra: dev
Requires-Dist: pytest; extra == "dev"
Requires-Dist: black; extra == "dev"
Requires-Dist: flake8; extra == "dev"
Provides-Extra: excel
Requires-Dist: openpyxl; extra == "excel"
Requires-Dist: pandas; extra == "excel"
